nominal_api/__init__.py
nominal_api/_impl.py
nominal_api/nominal-api.conjure.json
nominal_api/py.typed
nominal_api/api/__init__.py
nominal_api/api_ids/__init__.py
nominal_api/api_rids/__init__.py
nominal_api/attachments_api/__init__.py
nominal_api/authentication_api/__init__.py
nominal_api/authorization/__init__.py
nominal_api/comments_api/__init__.py
nominal_api/connect_download/__init__.py
nominal_api/datasource/__init__.py
nominal_api/datasource_api/__init__.py
nominal_api/datasource_pagination_api/__init__.py
nominal_api/event/__init__.py
nominal_api/ingest_api/__init__.py
nominal_api/ingest_manifest/__init__.py
nominal_api/ingest_workflow_api/__init__.py
nominal_api/module/__init__.py
nominal_api/module_internal/__init__.py
nominal_api/modules_api/__init__.py
nominal_api/persistent_compute_api/__init__.py
nominal_api/scout/__init__.py
nominal_api/scout_api/__init__.py
nominal_api/scout_asset_api/__init__.py
nominal_api/scout_assets/__init__.py
nominal_api/scout_catalog/__init__.py
nominal_api/scout_channelvariables_api/__init__.py
nominal_api/scout_chart_api/__init__.py
nominal_api/scout_chartdefinition_api/__init__.py
nominal_api/scout_checklistexecution_api/__init__.py
nominal_api/scout_checks_api/__init__.py
nominal_api/scout_comparisonnotebook_api/__init__.py
nominal_api/scout_comparisonrun_api/__init__.py
nominal_api/scout_compute_api/__init__.py
nominal_api/scout_compute_api_deprecated/__init__.py
nominal_api/scout_compute_resolved_api/__init__.py
nominal_api/scout_dataexport_api/__init__.py
nominal_api/scout_datareview_api/__init__.py
nominal_api/scout_datasource/__init__.py
nominal_api/scout_datasource_connection/__init__.py
nominal_api/scout_datasource_connection_api/__init__.py
nominal_api/scout_datasource_connection_api_influx/__init__.py
nominal_api/scout_favorites/__init__.py
nominal_api/scout_favorites_api/__init__.py
nominal_api/scout_integrations_api/__init__.py
nominal_api/scout_internal_search_api/__init__.py
nominal_api-0.1099.0.dist-info/METADATA
nominal_api-0.1099.0.dist-info/WHEEL
nominal_api-0.1099.0.dist-info/top_level.txt
nominal_api-0.1099.0.dist-info/RECORD
